{
"observatories":
    [
        {
        "observatory": "Hangon_Lintuasema",
        "locations": [
        "Bunkkeri",
        "Piha",
        "Eteläkärki",
        "Metsä",
        "Luoto Gåu"
        ],
        "types": [
        "Vakio",
        "Päivämuutto",
        "Yömuutto",
        "Hajahavainnot"
        ]
        },
        {
        "observatory": "Jurmon_Lintuasema",
        "locations": [
        "Korkein kohta",
        "Länsireitti"
        ],
        "types": [
        "Vakio",
        "Esimerkki 5",
        "Esimerkki 6",
        "Esimerkki 7"
        ]
        }
    ]
}